TB2J/Jdownfolder.py
TB2J/Jtensor.py
TB2J/MAE.py
TB2J/MAEGreen.py
TB2J/Oiju.py
TB2J/Oiju_epc.py
TB2J/__init__.py
TB2J/anisotropy.py
TB2J/basis.py
TB2J/citation.py
TB2J/contour.py
TB2J/density_matrix.py
TB2J/epc.py
TB2J/exchange.py
TB2J/exchangeCL2.py
TB2J/exchange_params.py
TB2J/exchange_pert.py
TB2J/exchange_qspace.py
TB2J/gpaw_wrapper.py
TB2J/green.py
TB2J/greentest.py
TB2J/io_merge.py
TB2J/kpoints.py
TB2J/myTB.py
TB2J/mycfr.py
TB2J/orbital_magmom.py
TB2J/orbmap.py
TB2J/pauli.py
TB2J/pert.py
TB2J/plot.py
TB2J/rotate_atoms.py
TB2J/rotate_siestaDM.py
TB2J/sisl_wrapper.py
TB2J/symmetrize_J.py
TB2J/tensor_rotate.py
TB2J/thetaphi.py
TB2J/utest.py
TB2J/utils.py
TB2J/versioninfo.py
TB2J/downfold/Hdownfolder.py
TB2J/external/__init__.py
TB2J/external/p_tqdm.py
TB2J/interfaces/__init__.py
TB2J/interfaces/gpaw_interface.py
TB2J/interfaces/lawaf_interface.py
TB2J/interfaces/manager.py
TB2J/interfaces/siesta_interface.py
TB2J/interfaces/wannier90_interface.py
TB2J/interfaces/abacus/__init__.py
TB2J/interfaces/abacus/abacus_api.py
TB2J/interfaces/abacus/abacus_wrapper.py
TB2J/interfaces/abacus/gen_exchange_abacus.py
TB2J/interfaces/abacus/orbital_api.py
TB2J/interfaces/abacus/stru_api.py
TB2J/interfaces/abacus/test_density_matrix.py
TB2J/interfaces/abacus/test_read_HRSR.py
TB2J/interfaces/abacus/test_read_stru.py
TB2J/io_exchange/__init__.py
TB2J/io_exchange/io_espins.py
TB2J/io_exchange/io_exchange.py
TB2J/io_exchange/io_multibinit.py
TB2J/io_exchange/io_tomsasd.py
TB2J/io_exchange/io_txt.py
TB2J/io_exchange/io_uppasd.py
TB2J/io_exchange/io_vampire.py
TB2J/magnon/__init__.py
TB2J/magnon/io_exchange2.py
TB2J/magnon/magnon3.py
TB2J/magnon/magnon_band.py
TB2J/magnon/magnon_dos.py
TB2J/magnon/magnon_io.py
TB2J/magnon/magnon_math.py
TB2J/magnon/plot.py
TB2J/magnon/plot_magnon_dos_cli.py
TB2J/magnon/structure.py
TB2J/mathutils/__init__.py
TB2J/mathutils/auto_kpath.py
TB2J/mathutils/fermi.py
TB2J/mathutils/fibonacci_sphere.py
TB2J/mathutils/kR_convert.py
TB2J/mathutils/lowdin.py
tb2j-0.9.12.20.dist-info/licenses/LICENSE
tb2j-0.9.12.20.dist-info/METADATA
tb2j-0.9.12.20.dist-info/WHEEL
tb2j-0.9.12.20.dist-info/entry_points.txt
tb2j-0.9.12.20.dist-info/top_level.txt
tb2j-0.9.12.20.dist-info/RECORD
