Metadata-Version: 2.4
Name: TB2J
Version: 0.9.12.20
Summary: TB2J: First principle to Heisenberg exchange J using tight-binding Green function method
Author-email: Xu He <mailhexu@gmail.com>
Maintainer-email: Xu He <mailhexu@gmail.com>
License: BSD-2-Clause
Project-URL: Homepage, https://github.com/mailhexu/TB2J
Project-URL: Documentation, https://tb2j.readthedocs.io/en/latest/
Project-URL: Repository, https://github.com/mailhexu/TB2J
Project-URL: Issues, https://github.com/mailhexu/TB2J/issues
Keywords: magnetism,DFT,Heisenberg,exchange,physics
Classifier: Development Status :: 3 - Alpha
Classifier: Programming Language :: Python :: 3
Classifier: Programming Language :: Python :: 3.6
Classifier: Programming Language :: Python :: 3.7
Classifier: Programming Language :: Python :: 3.8
Classifier: Programming Language :: Python :: 3.9
Classifier: Programming Language :: Python :: 3.10
Classifier: Programming Language :: Python :: 3.11
Classifier: Programming Language :: Python :: 3.12
Classifier: Programming Language :: Python :: 3.13
Classifier: Programming Language :: Python :: 3.14
Classifier: Operating System :: OS Independent
Classifier: Intended Audience :: Science/Research
Classifier: Topic :: Scientific/Engineering :: Chemistry
Classifier: Topic :: Scientific/Engineering :: Physics
Classifier: License :: OSI Approved :: BSD License
License-File: LICENSE
Requires-Dist: numpy
Requires-Dist: scipy<1.17,>1.9
Requires-Dist: matplotlib
Requires-Dist: ase>=3.19
Requires-Dist: tqdm
Requires-Dist: pathos
Requires-Dist: packaging>=20.0
Requires-Dist: HamiltonIO>=0.3.0
Requires-Dist: pre-commit
Requires-Dist: sympair>0.1.1
Requires-Dist: tomli>=2.0.0
Requires-Dist: tomli-w>=1.0.0
Requires-Dist: typing_extensions
Provides-Extra: siesta
Requires-Dist: sisl>=0.9.0; extra == "siesta"
Requires-Dist: netcdf4; extra == "siesta"
Provides-Extra: lawaf
Requires-Dist: lawaf>=0.2.3; extra == "lawaf"
Provides-Extra: all
Requires-Dist: sisl>=0.9.0; extra == "all"
Requires-Dist: netcdf4; extra == "all"
Requires-Dist: lawaf>=0.2.3; extra == "all"
Dynamic: license-file
